LICENCE
README.md
setup.py
torch_ac_simple/__init__.py
torch_ac_simple/agent.py
torch_ac_simple/config.py
torch_ac_simple/model.py
torch_ac_simple.egg-info/PKG-INFO
torch_ac_simple.egg-info/SOURCES.txt
torch_ac_simple.egg-info/dependency_links.txt
torch_ac_simple.egg-info/requires.txt
torch_ac_simple.egg-info/top_level.txt
torch_ac_simple/utils/__init__.py
torch_ac_simple/utils/env.py
torch_ac_simple/utils/format.py
torch_ac_simple/utils/other.py
torch_ac_simple/utils/storage.py